DFF_Synchronus_reset.srcs/sources_1/new/DFF.v
`timescale 1ns / 1ps
//////////////////////////////////////////////////////////////////////////////////
// Company: 
// Engineer: 
// 
// Create Date: 20.09.2024 23:54:25
// Design Name: 
// Module Name: DFF
// Project Name: 
// Target Devices: 
// Tool Versions: 
// Description: 
// 
// Dependencies: 
// 
// Revision:
// Revision 0.01 - File Created
// Additional Comments:
// 
//////////////////////////////////////////////////////////////////////////////////


module DFF(
 input clk,rst_n,
 input d,
 output reg q
    );
    
    always@(posedge clk)begin
    if (!rst_n) q<=0;
    else q<=d;
    end
endmodule

DFF_Synchronus_reset.srcs/sim_1/new/DFF_tb.v
module DFF_tb;
    reg clk, rst_n;
    reg d;
    wire q;

    // Instantiate the D Flip-Flop module
    DFF dff (.clk(clk), .rst_n(rst_n), .d(d), .q(q));

    // Generate clock with period of 4 units
    always #2 clk = ~clk;

    // Stimulus generation
    initial begin
        clk = 0; rst_n = 0; d = 0; 
        
        // Reset and start test case 1
        #3 rst_n = 1;
        repeat(6) begin
            d = $urandom_range(0, 1);
            #3;
        end
        
        // Reset again and start test case 2
        rst_n = 0; 
        #3 rst_n = 1;
        repeat(6) begin
            d = $urandom_range(0, 1);
            #3;
        end
        
        // Finish the simulation
        $finish;
    end

    // Dump waveform to a file for later viewing
    initial begin
        $dumpfile("dump.vcd");
        $dumpvars(1, DFF_tb);
    end

endmodule

DFF_Synchronus_reset.sim/sim_1/behav/xsim/dump.vcd
$date
   Sat Sep 21 00:27:33 2024
$end
$version
  2019.1
$end
$timescale
  1ps
$end
$scope module DFF_tb $end
$var reg 1 ! clk $end
$var reg 1 " rst_n $end
$var reg 1 # d $end
$var wire 1 $ q $end
$upscope $end
$enddefinitions $end
#0
$dumpvars
0!
0"
0#
x$
$end
#2000
1!
0$
#3000
1"
1#
#4000
0!
#6000
1!
0#
#8000
0!
#10000
1!
#12000
0!
#14000
1!
#16000
0!
#18000
1!
1#
1$
#20000
0!
#21000
0"
#22000
1!
0$
#24000
0!
1"
0#
#26000
1!
#27000
1#
#28000
0!
#30000
1!
1$
